reviutils/__init__.py
reviutils-1.5.0.dist-info/LICENSE
reviutils-1.5.0.dist-info/METADATA
reviutils-1.5.0.dist-info/WHEEL
reviutils-1.5.0.dist-info/top_level.txt
reviutils-1.5.0.dist-info/RECORD
